{"id":8,"folder":"008-mothers-day","category":"etc","title":["Ngày của mẹ","Mother's Day","母親節","母亲节","mǔ qīn jié"],"data":[["hoa cẩm chướng","Dianthus caryophyllus","康乃馨","康乃馨","kāng nǎi xīn"],["ôm","hug","擁抱","拥抱","yōng bào"],["thức dậy","wake up","起床","起床","qǐ chuáng"],["yêu","love","愛","爱","ài"],["lịch","calendar","日曆","日历","rì lì"],["sữa","milk","牛奶","牛奶","niú nǎi"],["lát bánh mì nướng","toast","土司","土司","tǔ sī"],["cốc sứ","mug","馬克杯","马克杯","mǎ kè bēi"],["giường","bed","床","床","chuáng"],["gối","pillow","枕頭","枕头","zhěn tou"],["truyền hình","TV","電視","电视","diàn shì"],["phòng khách","living room","客廳","客厅","kè tīng"]]}